ihk_ausbildungsnachweis_broker/__init__.py
ihk_ausbildungsnachweis_broker/_version.py
ihk_ausbildungsnachweis_broker/app.py
ihk_ausbildungsnachweis_broker/azubi_repo.py
tests/__init__.py
ihk_ausbildungsnachweis_broker-0.1.3.dist-info/METADATA
ihk_ausbildungsnachweis_broker-0.1.3.dist-info/WHEEL
ihk_ausbildungsnachweis_broker-0.1.3.dist-info/entry_points.txt
ihk_ausbildungsnachweis_broker-0.1.3.dist-info/top_level.txt
ihk_ausbildungsnachweis_broker-0.1.3.dist-info/RECORD
