Metadata-Version: 2.1
Name: ihk-ausbildungsnachweis-broker
Version: 0.1.3
Summary: IHK Ausbildungsnachweise workflow broker
Home-page: https://github.com/twyleg/ausbildungsnachweis_utils
Author: Torsten Wylegala
Author-email: mail@twyleg.de
License: GPL 3.0
Keywords: ihk ausbildungsnachweis pdf signature
Requires-Dist: ihk-ausbildungsnachweis-utilities
Requires-Dist: PyGithub ~=1.59.1
Requires-Dist: pygit2 ~=1.13.1
Requires-Dist: flask ~=2.3.3
Requires-Dist: werkzeug ~=2.3.7
